exosphere
