Metadata-Version: 1.0
Name: exosphere
Version: 0.1.0
Summary: Pre-built, useful Cloudformation stacks and commands to work with them.
Home-page: http://github.com/TheLaunchNinja/exosphere
Author: The Launch Ninja
Author-email: exosphere@thelaunch.ninja
License: UNKNOWN
Platform: UNKNOWN
